info_check_toolkits/__init__.py
info_check_toolkits/toolkits.py
info_check_toolkits-0.0.6.dist-info/LICENSE
info_check_toolkits-0.0.6.dist-info/METADATA
info_check_toolkits-0.0.6.dist-info/WHEEL
info_check_toolkits-0.0.6.dist-info/top_level.txt
info_check_toolkits-0.0.6.dist-info/RECORD
