Metadata-Version: 2.1
Name: info-check-toolkits
Version: 0.0.6
Summary: a set of toolkits for checking a dictionary with String values
Author: alicedyd
Author-email: alicedyd <xjw20020626@126.com>
License: MIT
Classifier: Programming Language :: Python :: 3
Classifier: License :: OSI Approved :: MIT License
Classifier: Operating System :: OS Independent
Requires-Python: >=3.8
License-File: LICENSE
